nautobot_lunch/__init__.py
nautobot_lunch/app-config-schema.json
nautobot_lunch/static/nautobot_lunch/docs/404.html
nautobot_lunch/static/nautobot_lunch/docs/admin/compatibility_matrix.html
nautobot_lunch/static/nautobot_lunch/docs/admin/install.html
nautobot_lunch/static/nautobot_lunch/docs/admin/release_notes/index.html
nautobot_lunch/static/nautobot_lunch/docs/admin/release_notes/version_1.0.html
nautobot_lunch/static/nautobot_lunch/docs/admin/uninstall.html
nautobot_lunch/static/nautobot_lunch/docs/admin/upgrade.html
nautobot_lunch/static/nautobot_lunch/docs/assets/_mkdocstrings.css
nautobot_lunch/static/nautobot_lunch/docs/assets/extra.css
nautobot_lunch/static/nautobot_lunch/docs/assets/favicon.ico
nautobot_lunch/static/nautobot_lunch/docs/assets/images/favicon.png
nautobot_lunch/static/nautobot_lunch/docs/assets/javascripts/bundle.b4d07000.min.js
nautobot_lunch/static/nautobot_lunch/docs/assets/javascripts/bundle.b4d07000.min.js.map
nautobot_lunch/static/nautobot_lunch/docs/assets/javascripts/lunr/min/lunr.ar.min.js
nautobot_lunch/static/nautobot_lunch/docs/assets/javascripts/lunr/min/lunr.da.min.js
nautobot_lunch/static/nautobot_lunch/docs/assets/javascripts/lunr/min/lunr.de.min.js
nautobot_lunch/static/nautobot_lunch/docs/assets/javascripts/lunr/min/lunr.du.min.js
nautobot_lunch/static/nautobot_lunch/docs/assets/javascripts/lunr/min/lunr.es.min.js
nautobot_lunch/static/nautobot_lunch/docs/assets/javascripts/lunr/min/lunr.fi.min.js
nautobot_lunch/static/nautobot_lunch/docs/assets/javascripts/lunr/min/lunr.fr.min.js
nautobot_lunch/static/nautobot_lunch/docs/assets/javascripts/lunr/min/lunr.hi.min.js
nautobot_lunch/static/nautobot_lunch/docs/assets/javascripts/lunr/min/lunr.hu.min.js
nautobot_lunch/static/nautobot_lunch/docs/assets/javascripts/lunr/min/lunr.hy.min.js
nautobot_lunch/static/nautobot_lunch/docs/assets/javascripts/lunr/min/lunr.it.min.js
nautobot_lunch/static/nautobot_lunch/docs/assets/javascripts/lunr/min/lunr.ja.min.js
nautobot_lunch-1.0.0.dist-info/LICENSE
nautobot_lunch-1.0.0.dist-info/METADATA
nautobot_lunch-1.0.0.dist-info/WHEEL
nautobot_lunch-1.0.0.dist-info/RECORD
