Metadata-Version: 2.1
Name: nautobot_lunch
Version: 1.0.0
Summary: Nautobot Lunch
Home-page: https://github.com/nlgotz/nautobot-app-lunch
License: Apache-2.0
Keywords: nautobot,nautobot-app,nautobot-plugin
Author: Nate Gotz
Author-email: nathan.gotz@gmail.com
Requires-Python: >=3.8,<3.12
Classifier: Development Status :: 5 - Production/Stable
Classifier: Intended Audience :: Developers
Classifier: License :: OSI Approved :: Apache Software License
Classifier: Programming Language :: Python :: 3
Classifier: Programming Language :: Python :: 3.8
Classifier: Programming Language :: Python :: 3.9
Classifier: Programming Language :: Python :: 3.10
Classifier: Programming Language :: Python :: 3.11
Provides-Extra: all
Requires-Dist: nautobot (>=2.0.0,<3.0.0)
Requires-Dist: yelpapi (>=2.5.1,<3.0.0)
Project-URL: Documentation, https://nautobot-lunch.readthedocs.io/projects/lunch/en/latest/
Project-URL: Repository, https://github.com/nlgotz/nautobot-app-lunch
